windmillusersettingv1/__init__.py
windmillusersettingv1/client/__init__.py
windmillusersettingv1/client/internal_usersetting_client.py
windmill_usersetting-1.0.0.5.dist-info/METADATA
windmill_usersetting-1.0.0.5.dist-info/WHEEL
windmill_usersetting-1.0.0.5.dist-info/top_level.txt
windmill_usersetting-1.0.0.5.dist-info/RECORD
