Metadata-Version: 2.1
Name: windmill-usersetting
Version: 1.0.0.5
Summary: sdk in python for windmill usersetting
Home-page: https://console.cloud.baidu-int.com/devops/icode/repos/baidu/themis/windmill-usersetting/tree/master
Author: yangtingyu01
Author-email: yangtingyu01@baidu.com
License: MIT
Classifier: Programming Language :: Python
Classifier: Programming Language :: Python :: 3
Classifier: Programming Language :: Python :: 3.7
Classifier: Programming Language :: Python :: 3.8
Classifier: Programming Language :: Python :: 3.9
Requires-Python: >=3.6
Requires-Dist: bce-python-sdk ==0.8.87
Requires-Dist: multidict ==6.0.4
Requires-Dist: bce-internal-sdk
